{
	"singleRun" : {
		"classes": ["algCtrl", "md-raised"],
		"ifClause": "true",
		"layout": "column",
		"layoutAlign": "center stretch"
	},
	"menuTrigger": {
		"classes": ["md-fab"],
		"ifClause": "true",
		"layout": "",
		"layoutAlign": ""
	},
	"iconBtn": {
		"classes": ["md-fab", "md-raised", "md-mini"],
		"ifClause": "true",
		"layout": "",
		"layoutAlign": ""
	},
	"textBtn": {
		"classes": ["md-raised"],
		"ifClause": "true",
		"layout": "",
		"layoutAlign": ""
	},
	"numInput": {
		"classes": ["md-block"],
		"ifClause": "true",
		"layout": "",
		"layoutAlign": ""
	},
	"slideMeasure": {
		"classes": [],
		"ifClause": "true",
		"layout": "row",
		"layoutAlign": "center center"
	},
	"rangeMeasure": {
		"classes": [],
		"ifClause": "true",
		"layout": "row",
		"layoutAlign": "center center"
	},
	"menu": {
		"classes": ["md-fab-top-right", "md-scale"],
		"ifClause": "true",
		"layout": "",
		"layoutAlign": ""
	},
	"guiGroup": {
		"classes": [],
		"ifClause": "true",
		"layout": "",
		"layoutAlign": ""
	},
	"select": {
		"classes": [],
		"ifClause": "true",
		"layout": "",
		"layoutAlign": ""
	},
	"accordTab": {
		"classes": ["accordContent", "animate-if"],
		"ifClause": "true",
		"layout": "",
		"layoutAlign": ""
	},
	"accordBtnOpen": {
		"type": "iconBtn",
		"properties": "iconBtn", 
		"id": "", 
		"label": "maximize", 
		"icon": "img/icons/baseline-remove-24px.svg", 
		"clickEvent": "changeTabState", 
		"tooltip": "", 
		"tooltipDir": ""
	},
	"accordBtnClosed": {
		"type": "iconBtn",
		"properties": "iconBtn", 
		"id": "", 
		"label": "minimize", 
		"icon": "img/icons/baseline-add-24px.svg", 
		"clickEvent": "changeTabState", 
		"tooltip": "", 
		"tooltipDir": ""
	}
}